kliptypek/__init__.py
kliptypek/main.py
kliptypek/parsing.py
kliptypek/process.py
kliptypek-0.0.2.dist-info/LICENSE
kliptypek-0.0.2.dist-info/METADATA
kliptypek-0.0.2.dist-info/WHEEL
kliptypek-0.0.2.dist-info/entry_points.txt
kliptypek-0.0.2.dist-info/top_level.txt
kliptypek-0.0.2.dist-info/RECORD
