Metadata-Version: 2.1
Name: kliptypek
Version: 0.0.2
Summary: Clipboard typer. Insert text from clipboard using simulated typing. 
Author-email: The220th <The220th@gmail.com>
Project-URL: Homepage, https://github.com/The220th/kliptypek
Project-URL: Issues, https://github.com/The220th/kliptypek/issues
Classifier: Programming Language :: Python :: 3
Classifier: License :: OSI Approved :: MIT License
Classifier: Operating System :: OS Independent
Requires-Python: >=3.7
License-File: LICENSE
Requires-Dist: argparse
Requires-Dist: pyperclip
Requires-Dist: pyautogui
